LICENSE
README.md
setup.py
styler/__init__.py
styler.egg-info/PKG-INFO
styler.egg-info/SOURCES.txt
styler.egg-info/dependency_links.txt
styler.egg-info/top_level.txt