Metadata-Version: 2.1
Name: styler
Version: 0.1.3.6
Summary: Multitool package for text editing.
Author: $udo
License-File: LICENSE
